torchfx/__init__.py
torchfx/effect.py
torchfx/py.typed
torchfx/typing.py
torchfx/wave.py
torchfx/filter/__base.py
torchfx/filter/__init__.py
torchfx/filter/fir.py
torchfx/filter/iir.py
torchfx/filter/utils.py
torchfx-0.2.1.dist-info/METADATA
torchfx-0.2.1.dist-info/WHEEL
torchfx-0.2.1.dist-info/entry_points.txt
torchfx-0.2.1.dist-info/licenses/LICENSE
torchfx-0.2.1.dist-info/RECORD
