Metadata-Version: 2.4
Name: torchfx
Version: 0.2.1
Summary: A GPU accelerated library for audio DSP based on PyTorch
Project-URL: Repository, https://github.com/matteospanio/torchfx
Project-URL: Documentation, https://matteospanio.github.io/torchfx/
Project-URL: Changelog, https://github.com/matteospanio/torchfx/blob/master/CHANGELOG
Author-email: Matteo Spanio <spanio@dei.unipd.it>
License:                     GNU GENERAL PUBLIC LICENSE
License-File: LICENSE
Keywords: accelerated,audio,dsp,gpu,performance,signal processing,torch,torchfx
Classifier: Development Status :: 3 - Alpha
Classifier: Environment :: GPU
Classifier: Intended Audience :: Developers
Classifier: Intended Audience :: Science/Research
Classifier: Intended Audience :: Telecommunications Industry
Classifier: License :: OSI Approved :: GNU General Public License v3 (GPLv3)
Classifier: Natural Language :: English
Classifier: Topic :: Multimedia :: Sound/Audio
Classifier: Topic :: Scientific/Engineering
Classifier: Typing :: Typed
Requires-Python: >=3.10
Requires-Dist: annotated-types>=0.7.0
Requires-Dist: numpy>=2.2.4
Requires-Dist: scipy>=1.15.2
Requires-Dist: soundfile>=0.13.1
Requires-Dist: torch>=2.6.0
Requires-Dist: torchaudio>=2.6.0
